openav/__garbage__.py
openav/__init__.py
openav/api/__init__.py
openav/api/augmentation.py
openav/api/download.py
openav/api/preprocess_audio.py
openav/api/preprocess_video.py
openav/api/recorder.py
openav/api/test_audio.py
openav/api/test_audiovisual.py
openav/api/test_video.py
openav/api/testing.py
openav/api/train_audio.py
openav/api/train_audiovisual.py
openav/api/train_video.py
openav/api/vad.py
openav/api/vad_gui.py
openav/api/vosk_sr.py
openav/modules/__init__.py
openav/modules/core/__init__.py
openav/modules/core/core.py
openav/modules/core/exceptions.py
openav/modules/core/language.py
openav/modules/core/logging.py
openav/modules/core/messages.py
openav/modules/core/settings.py
openav/modules/dataset_recording/__init__.py
openav/modules/dataset_recording/app.py
openav/modules/file_manager/__init__.py
openav/modules/file_manager/download.py
openav/modules/file_manager/file_manager.py
openav/modules/file_manager/json_manager.py
openav/modules/file_manager/unzip.py
openav/modules/file_manager/yaml_manager.py
openav/modules/lab/__init__.py
openav/modules/lab/audio.py
openav/modules/lab/audiovisual.py
openav/modules/lab/build.py
openav/modules/lab/video.py
openav/modules/lab/video_converter.py
openav/modules/locales/en/LC_MESSAGES/argparse.mo
openav/modules/locales/en/LC_MESSAGES/base.mo
openav/modules/locales/ru/LC_MESSAGES/argparse.mo
openav/modules/locales/ru/LC_MESSAGES/base.mo
openav/modules/nn/__init__.py
openav/modules/nn/av_dataset.py
openav/modules/nn/models.py
openav/modules/nn/utils.py
openav/modules/trml/__init__.py
openav/modules/trml/shell.py
openav/rsrs/__init__.py
openav/rsrs/favicon/__init__.py
openav-1.0.0a21.dist-info/LICENSE
openav-1.0.0a21.dist-info/METADATA
openav-1.0.0a21.dist-info/WHEEL
openav-1.0.0a21.dist-info/entry_points.txt
openav-1.0.0a21.dist-info/top_level.txt
openav-1.0.0a21.dist-info/RECORD
