Metadata-Version: 2.2
Name: openav
Version: 1.0.0a21
Summary: OpenAV
Home-page: https://github.com/DmitryRyumin/openav
Author: Dmitry Ryumin, Denis Ivanko, Nikolay Shilov, Maxim Markitantov, Alexey Karpov
Author-email: dl_03.03.1991@mail.ru, denis.ivanko11@gmail.com, nick@iias.spb.su, m.markitantov@yandex.ru, karpov@iias.spb.su
Maintainer: Dmitry Ryumin
Maintainer-email: dl_03.03.1991@mail.ru
License: MIT
Project-URL: Bug Reports, https://github.com/DmitryRyumin/openav/issues
Project-URL: Documentation, https://openav.readthedocs.io
Project-URL: Source Code, https://github.com/DmitryRyumin/openav/tree/main/openav
Project-URL: Download, https://github.com/DmitryRyumin/openav/tags
Keywords: OpenAV,LipReading,SpeechRecognition,SignalProcessing,DataAugmentation,ArtificialNeuralNetworks,DeepMachineLearning,TransferLearning,Statistics,ComputerVision,ArtificialIntelligence,Preprocessing
Classifier: Development Status :: 3 - Alpha
Classifier: Natural Language :: Russian
Classifier: Natural Language :: English
Classifier: Intended Audience :: Developers
Classifier: Intended Audience :: Education
Classifier: Intended Audience :: End Users/Desktop
Classifier: Intended Audience :: Science/Research
Classifier: Intended Audience :: Information Technology
Classifier: Intended Audience :: Science/Research
Classifier: License :: OSI Approved :: MIT License
Classifier: Programming Language :: Python
Classifier: Programming Language :: Python :: 3
Classifier: Programming Language :: Python :: 3.10
Classifier: Programming Language :: Python :: 3.11
Classifier: Programming Language :: Python :: 3.12
Classifier: Programming Language :: Python :: 3 :: Only
Classifier: Programming Language :: Python :: Implementation :: CPython
Classifier: Topic :: Scientific/Engineering
Classifier: Topic :: Scientific/Engineering :: Mathematics
Classifier: Topic :: Scientific/Engineering :: Artificial Intelligence
Classifier: Topic :: Scientific/Engineering :: Image Processing
Classifier: Topic :: Scientific/Engineering :: Image Recognition
Classifier: Topic :: Software Development
Classifier: Topic :: Software Development :: Libraries
Classifier: Topic :: Software Development :: Libraries :: Python Modules
Classifier: Topic :: Documentation
Classifier: Topic :: Documentation :: Sphinx
Classifier: Topic :: Multimedia :: Sound/Audio
Classifier: Topic :: Multimedia :: Sound/Audio :: Analysis
Classifier: Topic :: Multimedia :: Sound/Audio :: Speech
Classifier: Topic :: Software Development :: Libraries
Classifier: Topic :: Software Development :: Libraries :: Python Modules
Classifier: Topic :: Software Development :: Localization
Classifier: Topic :: Utilities
Classifier: Operating System :: MacOS :: MacOS X
Classifier: Operating System :: Microsoft :: Windows
Classifier: Operating System :: POSIX :: Linux
Classifier: Framework :: Jupyter
Classifier: Framework :: Jupyter :: JupyterLab :: 4
Classifier: Framework :: Sphinx
Requires-Python: >=3.9, <4
License-File: LICENSE
Requires-Dist: ipython==8.31.0
Requires-Dist: colorama==0.4.6
Requires-Dist: numpy==1.26.4
Requires-Dist: pandas==2.2.3
Requires-Dist: prettytable==3.12.0
Requires-Dist: torch==2.2.2
Requires-Dist: torchaudio==2.2.2
Requires-Dist: torchvision==0.17.2
Requires-Dist: av==14.0.1
Requires-Dist: filetype==1.2.0
Requires-Dist: vosk==0.3.44
Requires-Dist: requests==2.32.3
Requires-Dist: pyyaml==6.0.2
Requires-Dist: streamlit==1.41.1
Requires-Dist: watchdog==6.0.0
Requires-Dist: pymediainfo==6.1.0
Requires-Dist: pillow==11.0.0
Requires-Dist: imgaug==0.4.0
Requires-Dist: ffmpeg==1.4
Requires-Dist: librosa==0.10.2.post1
Requires-Dist: matplotlib==3.10.0
Requires-Dist: mediapipe==0.10.13
Requires-Dist: opencv_contrib_python==4.10.0.84
Requires-Dist: einops==0.8.0
Requires-Dist: lion_pytorch==0.2.3
Requires-Dist: scikit-learn==1.6.0
Requires-Dist: tqdm==4.67.1
Requires-Dist: seaborn==0.13.2
Requires-Dist: Flask==3.1.0
Dynamic: author
Dynamic: author-email
Dynamic: classifier
Dynamic: description
Dynamic: description-content-type
Dynamic: home-page
Dynamic: keywords
Dynamic: license
Dynamic: maintainer
Dynamic: maintainer-email
Dynamic: project-url
Dynamic: requires-dist
Dynamic: requires-python
Dynamic: summary
